{
  "site": "skewese",
  "title": "5000년의 신비를 밝히다: 최근 발굴된 고대 이집트 문명의 경이로운 발견들",
  "tags": [
    "고대이집트",
    "고고학",
    "피라미드",
    "사카라",
    "문명사",
    "역사발견",
    "고대문명"
  ],
  "categories": [],
  "keywords": [
    "고대 이집트 발견",
    "사카라 무덤군",
    "피라미드 비밀",
    "이집트 고고학"
  ],
  "meta_description": "투탕카멘의 무덤부터 최신 발굴된 사카라 무덤군까지, 고대 이집트의 놀라운 고고학적 발견들을 통해 드러난 문명의 비밀과 새로운 역사적 통찰을 소개합니다.",
  "created_at": "2025-08-12T14:11:02.662518",
  "file_path": "data\\wordpress_posts\\skewese\\20250812_141102_5000년의 신비를 밝히다 최근 발굴된 고대 이집트 문명의 경이로운 발견들.html",
  "status": "draft",
  "word_count": 2504,
  "estimated_reading_time": 8
}